{
  "id": "MAP_GRANITE_CAVE_B1F",
  "name": "GraniteCave_B1F",
  "layout": "LAYOUT_GRANITE_CAVE_B1F",
  "music": "MUS_VICTORY_ROAD",
  "region_map_section": "MAPSEC_MT_PYRE",
  "requires_flash": true,
  "weather": "WEATHER_NONE",
  "map_type": "MAP_TYPE_INDOOR",
  "allow_cycling": false,
  "allow_escaping": false,
  "allow_running": true,
  "show_map_name": true,
  "battle_scene": "MAP_BATTLE_SCENE_NORMAL",
  "connections": null,
  "object_events": [
    {
      "graphics_id": "OBJ_EVENT_GFX_ITEM_BALL",
      "x": 1,
      "y": 4,
      "elevation": 3,
      "movement_type": "MOVEMENT_TYPE_LOOK_AROUND",
      "movement_range_x": 0,
      "movement_range_y": 0,
      "trainer_type": "TRAINER_TYPE_NONE",
      "trainer_sight_or_berry_tree_id": "ITEM_POKE_BALL",
      "script": "Common_EventScript_FindItem",
      "flag": "FLAG_ITEM_GRANITE_CAVE_B1F_POKE_BALL"
    }
  ],
  "warp_events": [
    {
      "x": 6,
      "y": 19,
      "elevation": 0,
      "dest_map": "MAP_MT_PYRE_3F",
      "dest_warp_id": "6"
    },
    {
      "x": 5,
      "y": 19,
      "elevation": 0,
      "dest_map": "MAP_MT_PYRE_3F",
      "dest_warp_id": "6"
    },
    {
      "x": 7,
      "y": 19,
      "elevation": 0,
      "dest_map": "MAP_MT_PYRE_3F",
      "dest_warp_id": "6"
    }
  ],
  "coord_events": [],
  "bg_events": []
}
